newport_laser_diode_driver/__init__.py
newport_laser_diode_driver/newport_laser_diode_driver.py
newport_laser_diode_driver-1.1.0.dist-info/LICENSE.txt
newport_laser_diode_driver-1.1.0.dist-info/METADATA
newport_laser_diode_driver-1.1.0.dist-info/WHEEL
newport_laser_diode_driver-1.1.0.dist-info/top_level.txt
newport_laser_diode_driver-1.1.0.dist-info/RECORD
