Metadata-Version: 2.1
Name: newport-laser-diode-driver
Version: 1.1.0
Summary: Python library for interfacing with Newport Model 300-500B Series Laser Diode Driver
Home-page: https://github.com/NextZtepS/newport_laser_diode_driver
Author: NextZtepS
Author-email: natdanaiongarjvaja@gmail.com
License: MIT
License-File: LICENSE.txt
Requires-Dist: pyusb
Provides-Extra: dev
Requires-Dist: pytest ; extra == 'dev'
Requires-Dist: twine ; extra == 'dev'
